arkserver/__init__.py
arkserver/config.ini
arkserver/main.py
arkserver/py.typed
arkserver/service.py
arkserver/server/__init__.py
arkserver/server/api_functions.py
arkserver/server/base.py
arkserver/server/client_functions.py
arkserver/server/game_bot_server.py
arkserver/server/multi_server.py
arkserver/server/read.py
arkserver/server/server_functions.py
arkserver/server/single_server.py
lib/__init__.py
lib/configuration.py
arkserver-0.0.37.dist-info/LICENSE
arkserver-0.0.37.dist-info/METADATA
arkserver-0.0.37.dist-info/WHEEL
arkserver-0.0.37.dist-info/top_level.txt
arkserver-0.0.37.dist-info/RECORD
